<?xml version="1.0" ?><ItemLookupResponse xmlns="http://webservices.amazon.com/AWSECommerceService/2011-08-01"><OperationRequest><HTTPHeaders><Header Name="UserAgent" Value="Ruby"></Header></HTTPHeaders><RequestId>e52435f4-aee2-4819-a1c3-1712f2ec655c</RequestId><Arguments><Argument Name="AssociateTag" Value="cshs-22"></Argument><Argument Name="IdType" Value="ISBN"></Argument><Argument Name="ItemId" Value="097669400X"></Argument><Argument Name="Operation" Value="ItemLookup"></Argument><Argument Name="ResponseGroup" Value="Medium"></Argument><Argument Name="SearchIndex" Value="Books"></Argument><Argument Name="Service" Value="AWSECommerceService"></Argument><Argument Name="SubscriptionId" Value="1ZYN93KGC2KDTSNXKHG2"></Argument><Argument Name="Timestamp" Value="2017-09-22T01:19:58Z"></Argument><Argument Name="Signature" Value="wDpJKMz+JIH5Lye/zyvR3yfInYTPrXtToVaVyaAtw4E="></Argument></Arguments><RequestProcessingTime>0.1126187680000000</RequestProcessingTime></OperationRequest><Items><Request><IsValid>True</IsValid><ItemLookupRequest><IdType>ISBN</IdType><ItemId>097669400X</ItemId><ResponseGroup>Medium</ResponseGroup><SearchIndex>Books</SearchIndex><VariationPage>All</VariationPage></ItemLookupRequest></Request><Item><ASIN>097669400X</ASIN><DetailPageURL>https://www.amazon.co.jp/Agile-Web-Development-Rails-Pragmatic/dp/097669400X?SubscriptionId=1ZYN93KGC2KDTSNXKHG2&amp;tag=cshs-22&amp;linkCode=xm2&amp;camp=2025&amp;creative=165953&amp;creativeASIN=097669400X</DetailPageURL><ItemLinks><ItemLink><Description>Add To Wishlist</Description><URL>https://www.amazon.co.jp/gp/registry/wishlist/add-item.html?asin.0=097669400X&amp;SubscriptionId=1ZYN93KGC2KDTSNXKHG2&amp;tag=cshs-22&amp;linkCode=xm2&amp;camp=2025&amp;creative=5143&amp;creativeASIN=097669400X</URL></ItemLink><ItemLink><Description>Tell A Friend</Description><URL>https://www.amazon.co.jp/gp/pdp/taf/097669400X?SubscriptionId=1ZYN93KGC2KDTSNXKHG2&amp;tag=cshs-22&amp;linkCode=xm2&amp;camp=2025&amp;creative=5143&amp;creativeASIN=097669400X</URL></ItemLink><ItemLink><Description>All Customer Reviews</Description><URL>https://www.amazon.co.jp/review/product/097669400X?SubscriptionId=1ZYN93KGC2KDTSNXKHG2&amp;tag=cshs-22&amp;linkCode=xm2&amp;camp=2025&amp;creative=5143&amp;creativeASIN=097669400X</URL></ItemLink><ItemLink><Description>All Offers</Description><URL>https://www.amazon.co.jp/gp/offer-listing/097669400X?SubscriptionId=1ZYN93KGC2KDTSNXKHG2&amp;tag=cshs-22&amp;linkCode=xm2&amp;camp=2025&amp;creative=5143&amp;creativeASIN=097669400X</URL></ItemLink></ItemLinks><SalesRank>1043223</SalesRank><SmallImage><URL>https://images-fe.ssl-images-amazon.com/images/I/51lbXFwhFvL._SL75_.jpg</URL><Height Units="pixels">75</Height><Width Units="pixels">62</Width></SmallImage><MediumImage><URL>https://images-fe.ssl-images-amazon.com/images/I/51lbXFwhFvL._SL160_.jpg</URL><Height Units="pixels">160</Height><Width Units="pixels">133</Width></MediumImage><LargeImage><URL>https://images-fe.ssl-images-amazon.com/images/I/51lbXFwhFvL.jpg</URL><Height Units="pixels">500</Height><Width Units="pixels">416</Width></LargeImage><ImageSets><ImageSet Category="primary"><SwatchImage><URL>https://images-fe.ssl-images-amazon.com/images/I/51lbXFwhFvL._SL30_.jpg</URL><Height Units="pixels">30</Height><Width Units="pixels">25</Width></SwatchImage><SmallImage><URL>https://images-fe.ssl-images-amazon.com/images/I/51lbXFwhFvL._SL75_.jpg</URL><Height Units="pixels">75</Height><Width Units="pixels">62</Width></SmallImage><ThumbnailImage><URL>https://images-fe.ssl-images-amazon.com/images/I/51lbXFwhFvL._SL75_.jpg</URL><Height Units="pixels">75</Height><Width Units="pixels">62</Width></ThumbnailImage><TinyImage><URL>https://images-fe.ssl-images-amazon.com/images/I/51lbXFwhFvL._SL110_.jpg</URL><Height Units="pixels">110</Height><Width Units="pixels">92</Width></TinyImage><MediumImage><URL>https://images-fe.ssl-images-amazon.com/images/I/51lbXFwhFvL._SL160_.jpg</URL><Height Units="pixels">160</Height><Width Units="pixels">133</Width></MediumImage><LargeImage><URL>https://images-fe.ssl-images-amazon.com/images/I/51lbXFwhFvL.jpg</URL><Height Units="pixels">500</Height><Width Units="pixels">416</Width></LargeImage></ImageSet></ImageSets><ItemAttributes><Author>David Thomas</Author><Author>David Heinemeier Hansson</Author><Author>Leon Breedt</Author><Binding>ペーパーバック</Binding><EAN>9780976694007</EAN><EANList><EANListElement>9780976694007</EANListElement><EANListElement>0852766001087</EANListElement></EANList><ISBN>097669400X</ISBN><ItemDimensions><Height Units="100分の1インチ">900</Height><Length Units="100分の1インチ">750</Length><Width Units="100分の1インチ">105</Width></ItemDimensions><Label>Pragmatic Bookshelf</Label><Languages><Language><Name>英語</Name><Type>Published</Type></Language><Language><Name>英語</Name><Type>Original Language</Type></Language><Language><Name>英語</Name><Type>Unknown</Type></Language></Languages><ListPrice><Amount>4059</Amount><CurrencyCode>JPY</CurrencyCode><FormattedPrice>￥ 4,059</FormattedPrice></ListPrice><Manufacturer>Pragmatic Bookshelf</Manufacturer><NumberOfItems>1</NumberOfItems><NumberOfPages>558</NumberOfPages><PackageDimensions><Height Units="100分の1インチ">100</Height><Length Units="100分の1インチ">900</Length><Weight Units="100分の1ポンド">175</Weight><Width Units="100分の1インチ">750</Width></PackageDimensions><ProductGroup>Book</ProductGroup><ProductTypeName>ABIS_BOOK</ProductTypeName><PublicationDate>2005-09-22</PublicationDate><Publisher>Pragmatic Bookshelf</Publisher><Studio>Pragmatic Bookshelf</Studio><Title>Agile Web Development With Rails: A Pragmatic Guide (The Facets of Ruby Series)</Title><UPC>852766001087</UPC><UPCList><UPCListElement>852766001087</UPCListElement></UPCList></ItemAttributes><OfferSummary><LowestNewPrice><Amount>4567</Amount><CurrencyCode>JPY</CurrencyCode><FormattedPrice>￥ 4,567</FormattedPrice></LowestNewPrice><LowestUsedPrice><Amount>99</Amount><CurrencyCode>JPY</CurrencyCode><FormattedPrice>￥ 99</FormattedPrice></LowestUsedPrice><TotalNew>2</TotalNew><TotalUsed>12</TotalUsed><TotalCollectible>0</TotalCollectible><TotalRefurbished>0</TotalRefurbished></OfferSummary></Item></Items></ItemLookupResponse>